Workbook

Sheet Simulador Porte
A1: SIMULADOR SIMPLIFICADO DE PORTE DO PRODUTOR RURAL
A2: Preencha os campos amarelos. O porte será calculado automaticamente pelas faixas da RBA e pelas regras especiais do Pronaf, Pronamp e rendimentos de atividades não rurais.
A4: 1. INFORMAÇÕES DO PRODUTOR | F4: 3. RESULTADO PARA COLOCAR NO CAPES
A5: Campo | B5: Preenchimento | C5: Orientação | F5: ='Cálculos - não editar'!B27 -> PREENCHER RENDAS
A6: CAF ativa com enquadramento Pronaf? | C6: Marque SIM somente quando o CAF estiver válido e indicar o enquadramento no Pronaf.
A7: Condição da terra | C7: Informação utilizada para verificar as condições do Pronamp.
A8: Ano-base (opcional) | C8: Utilize um ano civil de produção normal, verificado entre os três últimos anos. | F8: Indicador | G8: Resultado
A9: Condomínio/parceria? | C9: Quando SIM, utilize as rendas do condômino ou parceiro com a maior RBA. | F9: RBA | G9: ='Cálculos - não editar'!B17 -> 0
F10: Receita Bruta Total | G10: ='Cálculos - não editar'!B20 -> 0
A11: 2. RENDAS ANUAIS | F11: % da atividade agropecuária | G11: ='Cálculos - não editar'!B22 -> 0
A12: Item | B12: Tipo de renda | C12: Descrição (opcional) | D12: Valor anual | F12: % de atividades não rurais | G12: ='Cálculos - não editar'!B23 -> 0
A13: 1 | D13: 200000
A14: 2 | D14: 100000
A15: 3 | F15: REGRA APLICADA
A16: 4 | F16: ='Cálculos - não editar'!B28 -> Informe pelo menos uma renda anual para realizar a classificação.
A17: 5
A18: 6
A19: 7
A20: 8
A21: 9
A22: 10
A23: 11
A24: 12
F25: VERIFICAÇÕES
A26: Dica: utilize “Outras rendas de atividade não rural” para rendas decorrentes de trabalho ou negócio não rural. Aposentadorias, benefícios, aluguéis e aplicações possuem opções próprias. | F26: CAF/Pronaf | G26: ='Cálculos - não editar'!B30 -> NÃO INFORMADO / NÃO ENQUADRADO
F27: Condições do Pronamp | G27: ='Cálculos - não editar'!B25 -> NÃO APLICÁVEL
F28: Regra de atividade não rural > 20% | G28: ='Cálculos - não editar'!B26 -> NÃO APLICÁVEL
F29: Base normativa determinante | G29: ='Cálculos - não editar'!B29 -> -
A31: Este simulador é um apoio operacional. A cooperativa deve validar os documentos, a representatividade do período e o enquadramento normativo do caso concreto.

Sheet Regras 
A1: REGRAS DE CLASSIFICAÇÃO DO PORTE
A2: Baseadas no Manual de Crédiro Rural
A4: Porte | B4: Regra pela RBA | C4: Regra especial | D4: Conclusão prática | E4: Base normativa
A5: PEQUENO | B5: RBA de até R$ 500.000,00. | C5: CAF válido com enquadramento no Pronaf. | D5: Pode ser pequeno pela faixa da RBA ou pelo enquadramento formal no Pronaf. | E5: MCR 1-2-3(a), 1-2-5(e) e MCR 10-2.
A6: MÉDIO | B6: RBA acima de R$ 500.000,00 até R$ 3.500.000,00. | C6: Atendimento às condições do Pronamp. | D6: Pode permanecer médio pela faixa da RBA mesmo sem atender ao Pronamp, desde que não incida outra regra especial. | E6: MCR 1-2-3(b), 1-2-5(f) e MCR 8-1.
A7: GRANDE | B7: RBA acima de R$ 3.500.000,00. | C7: Rendimentos de atividades não rurais superiores a 20% da Receita Bruta Total, ressalvados Pronaf e Pronamp. | D7: Pode ser grande pelo valor da RBA ou pela composição da receita. | E7: MCR 1-2-3(c) e 1-2-5(g).
A9: ORDEM DE ANÁLISE
A10: 1 | B10: Apurar a RBA | C10: Somar as receitas de todas as atividades rurais.
A11: 2 | B11: Calcular o porte-base | C11: Aplicar as faixas de R$ 500 mil e R$ 3,5 milhões.
A12: 3 | B12: Verificar Pronaf | C12: CAF válido com enquadramento no Pronaf caracteriza pequeno produtor.
A13: 4 | B13: Verificar Pronamp | C13: Condição da terra, RBT até R$ 3,5 milhões e mínimo de 80% agropecuário.
A14: 5 | B14: Verificar a regra dos 20% | C14: Rendimentos de atividades não rurais superiores a 20% da RBT caracterizam grande produtor, ressalvadas as regras especiais.
A16: BASE NORMATIVA E FONTES
A17: Norma | B17: Conteúdo utilizado | C17: Fonte oficial
A18: MCR 1-2-3 e 1-2-5 | B18: Faixas da RBA, composição, ano representativo, condomínio/parceria e regras especiais. | C18: https://www3.bcb.gov.br/mcr
A19: Resolução CMN nº 5.235/2025 | B19: Limites de R$ 500 mil e R$ 3,5 milhões. | C19: https://www.bcb.gov.br/estabilidadefinanceira/exibenormativo?numero=5235&tipo=Resolu%C3%A7%C3%A3o+CMN
A20: MCR 8-1 / Resolução CMN nº 5.229/2025 | B20: Condições do Pronamp e limite da renda bruta anual. | C20: https://www.bcb.gov.br/estabilidadefinanceira/exibenormativo?numero=5229&tipo=Resolu%C3%A7%C3%A3o+CMN
A21: MCR 10-2 / Resolução CMN nº 5.230/2025 | B21: CAF e critérios de enquadramento no Pronaf. | C21: https://www.bcb.gov.br/estabilidadefinanceira/exibenormativo?numero=5230&tipo=Resolu%C3%A7%C3%A3o+CMN
A22: Atualização considerada | B22: MCR nº 757, de 17/07/2026, conforme texto fornecido para elaboração da planilha. | C22: https://www3.bcb.gov.br/mcr
A24: OBSERVAÇÃO
A25: A classificação do porte do produtor rural deve considerar, de forma conjunta, a Receita Bruta Agropecuária Anual (RBA) e as regras especiais previstas no Manual de Crédito Rural. O porte-base é definido pelas faixas da RBA. Em seguida, devem ser verificados o CAF válido com enquadramento no Pronaf, as condições do Pronamp e a participação dos rendimentos provenientes de atividades não rurais na Receita Bruta Total. O porte não se confunde com a elegibilidade a uma linha específica de crédito. Assim, o produtor pode permanecer classificado como médio pela faixa da RBA mesmo sem atender às condições do Pronamp, desde que não seja alcançado por outra regra especial de classificação.
A30: A RBA deve corresponder ao somatório das receitas provenientes de todas as atividades rurais e ser representativa de um ano civil de produção normal, verificado entre os três últimos anos. Em condomínio ou parceria, utiliza-se a classificação do produtor com a maior RBA.

Sheet Cálculos - não editar
A1: PARÂMETROS E CÁLCULOS — NÃO EDITAR
A2: Tipo de renda | B2: Categoria | C2: Integra RBA? | D2: Compõe os 80% agropecuários do Pronamp? | E2: Compõe a parcela não agropecuária do Pronamp? | F2: Atividade não rural para regra dos 20%? | H2: Item | I2: Tipo informado | J2: Valor | K2: Integra RBA? | L2: Agropecuária Pronamp? | M2: Não agro Pronamp? | N2: Atividade não rural?
A3: Produção agrícola | B3: ATIVIDADE AGROPECUÁRIA | C3: SIM | D3: SIM | E3: NÃO | F3: NÃO | H3: 1 | I3: ='Simulador Porte'!B13 -> 0 | J3: ='Simulador Porte'!D13 -> 200000 | K3: =IF(I3="","",VLOOKUP(I3,$A$3:$F$15,3,FALSE)) -> #N/A | L3: =IF(I3="","",VLOOKUP(I3,$A$3:$F$15,4,FALSE)) -> #N/A | M3: =IF(I3="","",VLOOKUP(I3,$A$3:$F$15,5,FALSE)) -> #N/A | N3: =IF(I3="","",VLOOKUP(I3,$A$3:$F$15,6,FALSE)) -> #N/A
A4: Produção pecuária | B4: ATIVIDADE AGROPECUÁRIA | C4: SIM | D4: SIM | E4: NÃO | F4: NÃO | H4: 2 | I4: ='Simulador Porte'!B14 -> 0 | J4: ='Simulador Porte'!D14 -> 100000 | K4: =IF(I4="","",VLOOKUP(I4,$A$3:$F$15,3,FALSE)) -> #N/A | L4: =IF(I4="","",VLOOKUP(I4,$A$3:$F$15,4,FALSE)) -> #N/A | M4: =IF(I4="","",VLOOKUP(I4,$A$3:$F$15,5,FALSE)) -> #N/A | N4: =IF(I4="","",VLOOKUP(I4,$A$3:$F$15,6,FALSE)) -> #N/A
A5: Receita de entidade integradora (agropecuária) | B5: ATIVIDADE AGROPECUÁRIA | C5: SIM | D5: SIM | E5: NÃO | F5: NÃO | H5: 3 | I5: ='Simulador Porte'!B15 -> 0 | J5: ='Simulador Porte'!D15 -> 0 | K5: =IF(I5="","",VLOOKUP(I5,$A$3:$F$15,3,FALSE)) -> #N/A | L5: =IF(I5="","",VLOOKUP(I5,$A$3:$F$15,4,FALSE)) -> #N/A | M5: =IF(I5="","",VLOOKUP(I5,$A$3:$F$15,5,FALSE)) -> #N/A | N5: =IF(I5="","",VLOOKUP(I5,$A$3:$F$15,6,FALSE)) -> #N/A
A6: Extrativismo vegetal ou animal | B6: OUTRA ATIVIDADE RURAL | C6: SIM | D6: NÃO | E6: SIM | F6: NÃO | H6: 4 | I6: ='Simulador Porte'!B16 -> 0 | J6: ='Simulador Porte'!D16 -> 0 | K6: =IF(I6="","",VLOOKUP(I6,$A$3:$F$15,3,FALSE)) -> #N/A | L6: =IF(I6="","",VLOOKUP(I6,$A$3:$F$15,4,FALSE)) -> #N/A | M6: =IF(I6="","",VLOOKUP(I6,$A$3:$F$15,5,FALSE)) -> #N/A | N6: =IF(I6="","",VLOOKUP(I6,$A$3:$F$15,6,FALSE)) -> #N/A
A7: Serviços afins prestados pelo produtor Rural | B7: OUTRA ATIVIDADE RURAL | C7: SIM | D7: NÃO | E7: SIM | F7: NÃO | H7: 5 | I7: ='Simulador Porte'!B17 -> 0 | J7: ='Simulador Porte'!D17 -> 0 | K7: =IF(I7="","",VLOOKUP(I7,$A$3:$F$15,3,FALSE)) -> #N/A | L7: =IF(I7="","",VLOOKUP(I7,$A$3:$F$15,4,FALSE)) -> #N/A | M7: =IF(I7="","",VLOOKUP(I7,$A$3:$F$15,5,FALSE)) -> #N/A | N7: =IF(I7="","",VLOOKUP(I7,$A$3:$F$15,6,FALSE)) -> #N/A
A8: Outras receitas de atividade rural | B8: OUTRA ATIVIDADE RURAL | C8: SIM | D8: SIM | E8: NÃO | F8: NÃO | H8: 6 | I8: ='Simulador Porte'!B18 -> 0 | J8: ='Simulador Porte'!D18 -> 0 | K8: =IF(I8="","",VLOOKUP(I8,$A$3:$F$15,3,FALSE)) -> #N/A | L8: =IF(I8="","",VLOOKUP(I8,$A$3:$F$15,4,FALSE)) -> #N/A | M8: =IF(I8="","",VLOOKUP(I8,$A$3:$F$15,5,FALSE)) -> #N/A | N8: =IF(I8="","",VLOOKUP(I8,$A$3:$F$15,6,FALSE)) -> #N/A
A9: Salário / honorários / pró-labore | B9: ATIVIDADE NÃO RURAL | C9: NÃO | D9: NÃO | E9: SIM | F9: SIM | H9: 7 | I9: ='Simulador Porte'!B19 -> 0 | J9: ='Simulador Porte'!D19 -> 0 | K9: =IF(I9="","",VLOOKUP(I9,$A$3:$F$15,3,FALSE)) -> #N/A | L9: =IF(I9="","",VLOOKUP(I9,$A$3:$F$15,4,FALSE)) -> #N/A | M9: =IF(I9="","",VLOOKUP(I9,$A$3:$F$15,5,FALSE)) -> #N/A | N9: =IF(I9="","",VLOOKUP(I9,$A$3:$F$15,6,FALSE)) -> #N/A
A10: Rendimentos empresarial não rural | B10: ATIVIDADE NÃO RURAL | C10: NÃO | D10: NÃO | E10: SIM | F10: SIM | H10: 8 | I10: ='Simulador Porte'!B20 -> 0 | J10: ='Simulador Porte'!D20 -> 0 | K10: =IF(I10="","",VLOOKUP(I10,$A$3:$F$15,3,FALSE)) -> #N/A | L10: =IF(I10="","",VLOOKUP(I10,$A$3:$F$15,4,FALSE)) -> #N/A | M10: =IF(I10="","",VLOOKUP(I10,$A$3:$F$15,5,FALSE)) -> #N/A | N10: =IF(I10="","",VLOOKUP(I10,$A$3:$F$15,6,FALSE)) -> #N/A
A11: Declaração de Renda | B11: ATIVIDADE NÃO RURAL | C11: NÃO | D11: NÃO | E11: SIM | F11: SIM | H11: 9 | I11: ='Simulador Porte'!B21 -> 0 | J11: ='Simulador Porte'!D21 -> 0 | K11: =IF(I11="","",VLOOKUP(I11,$A$3:$F$15,3,FALSE)) -> #N/A | L11: =IF(I11="","",VLOOKUP(I11,$A$3:$F$15,4,FALSE)) -> #N/A | M11: =IF(I11="","",VLOOKUP(I11,$A$3:$F$15,5,FALSE)) -> #N/A | N11: =IF(I11="","",VLOOKUP(I11,$A$3:$F$15,6,FALSE)) -> #N/A
A12: Aposentadoria / benefício / pensão | B12: ATIVIDADE NÃO RURAL | C12: NÃO | D12: NÃO | E12: SIM | F12: SIM | H12: 10 | I12: ='Simulador Porte'!B22 -> 0 | J12: ='Simulador Porte'!D22 -> 0 | K12: =IF(I12="","",VLOOKUP(I12,$A$3:$F$15,3,FALSE)) -> #N/A | L12: =IF(I12="","",VLOOKUP(I12,$A$3:$F$15,4,FALSE)) -> #N/A | M12: =IF(I12="","",VLOOKUP(I12,$A$3:$F$15,5,FALSE)) -> #N/A | N12: =IF(I12="","",VLOOKUP(I12,$A$3:$F$15,6,FALSE)) -> #N/A
A13: Aluguel | B13: ATIVIDADE NÃO RURAL | C13: NÃO | D13: NÃO | E13: SIM | F13: SIM | H13: 11 | I13: ='Simulador Porte'!B23 -> 0 | J13: ='Simulador Porte'!D23 -> 0 | K13: =IF(I13="","",VLOOKUP(I13,$A$3:$F$15,3,FALSE)) -> #N/A | L13: =IF(I13="","",VLOOKUP(I13,$A$3:$F$15,4,FALSE)) -> #N/A | M13: =IF(I13="","",VLOOKUP(I13,$A$3:$F$15,5,FALSE)) -> #N/A | N13: =IF(I13="","",VLOOKUP(I13,$A$3:$F$15,6,FALSE)) -> #N/A
A14: Aplicações financeiras | B14: ATIVIDADE NÃO RURAL | C14: NÃO | D14: NÃO | E14: SIM | F14: SIM | H14: 12 | I14: ='Simulador Porte'!B24 -> 0 | J14: ='Simulador Porte'!D24 -> 0 | K14: =IF(I14="","",VLOOKUP(I14,$A$3:$F$15,3,FALSE)) -> #N/A | L14: =IF(I14="","",VLOOKUP(I14,$A$3:$F$15,4,FALSE)) -> #N/A | M14: =IF(I14="","",VLOOKUP(I14,$A$3:$F$15,5,FALSE)) -> #N/A | N14: =IF(I14="","",VLOOKUP(I14,$A$3:$F$15,6,FALSE)) -> #N/A
A15: Outras rendas não agropecuárias | B15: ATIVIDADE NÃO RURAL | C15: NÃO | D15: NÃO | E15: SIM | F15: SIM
A17: RBA | B17: =SUMIF($K$3:$K$14,"SIM",$J$3:$J$14) -> 0
A18: Compõe os 80% agropecuários do Pronamp? | B18: =SUMIF($L$3:$L$14,"SIM",$J$3:$J$14) -> 0
A19: Demais rendas não agropecuárias | B19: =SUMIF($M$3:$M$14,"SIM",$J$3:$J$14) -> 0
A20: Receita Bruta Total | B20: =B18+B19 -> 0
A21: Rendimentos de atividades não rurais | B21: =SUMIF($N$3:$N$14,"SIM",$J$3:$J$14) -> 0
A22: % atividade agropecuária | B22: =IF(B20=0,0,B18/B20) -> 0
A23: % atividades não rurais | B23: =IF(B20=0,0,B21/B20) -> 0
A24: Porte-base | B24: =IF(B20=0,"PREENCHER RENDAS",IF(B17<=500000,"PEQUENO",IF(B17<=3500000,"MÉDIO","GRANDE"))) -> PREENCHER RENDAS
A25: Atende Pronamp? | B25: =IF(B20=0,"NÃO APLICÁVEL",IF('Simulador Porte'!B7="SELECIONAR","INFORMAR CONDIÇÃO DA TERRA",IF(AND(OR('Simulador Porte'!B7="PROPRIETÁRIO RURAL",'Simulador Porte'!B7="POSSEIRO",'Simulador Porte'!B7="ARRENDATÁRIO",'Simulador Porte'!B7="PARCEIRO"),B20<=3500000,B22>=80%),"SIM","NÃO"))) -> NÃO APLICÁVEL
A26: Regra dos 20%? | B26: =IF(B20=0,"NÃO APLICÁVEL",IF(B23>20%,"SIM","NÃO")) -> NÃO APLICÁVEL
A27: Porte final | B27: =IF(UPPER('Simulador Porte'!B6)="SIM","PEQUENO PRODUTOR",IF(B20=0,"PREENCHER RENDAS",IF(B25="INFORMAR CONDIÇÃO DA TERRA","INFORMAR CONDIÇÃO DA TERRA",IF(B25="SIM","MÉDIO PRODUTOR",IF(B26="SIM","GRANDE PRODUTOR",IF(B24="PEQUENO","PEQUENO PRODUTOR",IF(B24="MÉDIO","MÉDIO PRODUTOR","GRANDE PRODUTOR"))))))) -> PREENCHER RENDAS
A28: Justificativa | B28: =IF(B27="PREENCHER RENDAS", "Informe pelo menos uma renda anual para realizar a classificação.", IF(B27="INFORMAR CONDIÇÃO DA TERRA", "Selecione a condição de exploração da terra para concluir a análise das condições do Pronamp.", IF(UPPER('Simulador Porte'!B6)="SIM", "O produtor foi classificado como PEQUENO PRODUTOR por possuir CAF válido com enquadramento no Pronaf, conforme a regra especial prevista no MCR 1-2-5(e).", IF(B25="SIM", "A RBA apurada foi de "&TEXT(B17,"R$ #.##0,00")&", valor que, considerado isoladamente, corresponderia ao porte "&B24&_xlfn._LONGTEXT(" pela faixa da RBA. Entretanto, não foi informado CAF válido com enquadramento no Pronaf e, por esse motivo, o produtor não é elegível ao Pronaf nesta simulação. Por outro lado, o produtor atende cumulativamente às condições do Pronamp: condição de explor","ação da terra admitida, Receita Bruta Total de ")&TEXT(B20,"R$ #.##0,00")&", dentro do limite de R$ 3.500.000,00, e "&TEXT(B22,"0,00%")&" da renda originária da atividade agropecuária, percentual igual ou superior a 80%. Assim, conforme o MCR 1-2-5(f), o beneficiário enquadrado nas condições do Pronamp é considerado MÉDIO PRODUTOR. Portanto, o porte final apurado é MÉDIO PRODUTOR.", IF(B26="SIM", "O produtor foi classificado como GRANDE PRODUTOR porque os rendimentos provenientes de atividades não rurais representam "&TEXT(B23,"0,00%")&" da Receita Bruta Total, percentual superior a 20%, conforme o MCR 1-2-5(g).", IF(B24="PEQUENO", "O produtor foi classificado como PEQUENO PRODUTOR porque a RBA apurada foi de "&TEXT(B17,"R$ #.##0,00")&", valor dentro do limite de R$ 500.000,00, e não foi identificada regra especial que alterasse essa classificação.", IF(B24="MÉDIO", "O produtor foi classificado como MÉDIO PRODUTOR porque a RBA apurada foi de "&TEXT(B17,"R$ #.##0,00")&", valor acima de R$ 500.000,00 e até R$ 3.500.000,00, e não foi identificada regra especial que alterasse essa classificação.", "O produtor foi classificado como GRANDE PRODUTOR porque a RBA apurada foi de "&TEXT(B17,"R$ #.##0,00")&", valor superior a R$ 3.500.000,00." ))))))) -> Informe pelo menos uma renda anual para realizar a classificação.
A29: Base normativa | B29: =IF(B27="PREENCHER RENDAS","-",IF(B27="INFORMAR CONDIÇÃO DA TERRA","Preenchimento pendente",IF(UPPER('Simulador Porte'!B6)="SIM","MCR 1-2-5(e) e MCR 10-2",IF(B25="SIM","MCR 1-2-5(f) e MCR 8-1",IF(B26="SIM","MCR 1-2-5(g)",IF(B24="PEQUENO","MCR 1-2-3(a)",IF(B24="MÉDIO","MCR 1-2-3(b)","MCR 1-2-3(c)"))))))) -> -
A30: CAF/Pronaf | B30: =IF(UPPER('Simulador Porte'!B6)="SIM","ENQUADRADO","NÃO INFORMADO / NÃO ENQUADRADO") -> NÃO INFORMADO / NÃO ENQUADRADO
A32: Fontes: Manual de Crédito Rural – MCR 1-2-3 e 1-2-5; MCR 8-1; MCR 10-2. Atualização considerada: MCR nº 757, de 17/07/2026, conforme o texto normativo fornecido. Consulta oficial: https://www3.bcb.gov.br/mcr
